odoo/addons/hr_employee_ssn/README.rst
odoo/addons/hr_employee_ssn/__init__.py
odoo/addons/hr_employee_ssn/__manifest__.py
odoo/addons/hr_employee_ssn/i18n/es.po
odoo/addons/hr_employee_ssn/i18n/fr.po
odoo/addons/hr_employee_ssn/i18n/hr_employee_ssn.pot
odoo/addons/hr_employee_ssn/i18n/it.po
odoo/addons/hr_employee_ssn/readme/CONTRIBUTORS.rst
odoo/addons/hr_employee_ssn/readme/DESCRIPTION.rst
odoo/addons/hr_employee_ssn/static/description/icon.png
odoo/addons/hr_employee_ssn/static/description/index.html
odoo/addons/hr_employee_ssn/views/hr_employee_views.xml
odoo13_addon_hr_employee_ssn-13.0.1.0.1.dev7.dist-info/METADATA
odoo13_addon_hr_employee_ssn-13.0.1.0.1.dev7.dist-info/WHEEL
odoo13_addon_hr_employee_ssn-13.0.1.0.1.dev7.dist-info/top_level.txt
odoo13_addon_hr_employee_ssn-13.0.1.0.1.dev7.dist-info/RECORD
